itk_iofdf-1.1.1.dist-info/RECORD
itk_iofdf-1.1.1.dist-info/WHEEL
itk_iofdf-1.1.1.dist-info/METADATA
itk_iofdf-1.1.1.dist-info/licenses/LICENSE
itk_iofdf.libs/libtbb-f489fd38.so.12.9
itk/_IOFDFPython.cpython-39-x86_64-linux-gnu.so
itk/itkFDFImageIOPython.py
itk/IOFDFPython.py
itk/Configuration/IOFDFConfig.py
itk/Configuration/IOFDF_snake_case.py
